django_tasks/__init__.py
django_tasks/apps.py
django_tasks/base.py
django_tasks/checks.py
django_tasks/compat.py
django_tasks/exceptions.py
django_tasks/py.typed
django_tasks/signals.py
django_tasks/utils.py
django_tasks/backends/__init__.py
django_tasks/backends/base.py
django_tasks/backends/dummy.py
django_tasks/backends/immediate.py
django_tasks/backends/rq.py
django_tasks/backends/database/__init__.py
django_tasks/backends/database/admin.py
django_tasks/backends/database/apps.py
django_tasks/backends/database/backend.py
django_tasks/backends/database/models.py
django_tasks/backends/database/signal_handlers.py
django_tasks/backends/database/utils.py
django_tasks/backends/database/management/commands/db_worker.py
django_tasks/backends/database/management/commands/prune_db_task_results.py
django_tasks/backends/database/migrations/0001_initial.py
django_tasks/backends/database/migrations/0002_alter_dbtaskresult_options.py
django_tasks/backends/database/migrations/0003_dbtaskresult_enqueued_at_dbtaskresult_finished_at.py
django_tasks/backends/database/migrations/0004_dbtaskresult_started_at.py
django_tasks/backends/database/migrations/0005_alter_dbtaskresult_priority_and_more.py
django_tasks/backends/database/migrations/0006_alter_dbtaskresult_args_kwargs_and_more.py
django_tasks/backends/database/migrations/0007_add_separate_results_fields.py
django_tasks/backends/database/migrations/0008_separate_results_field.py
django_tasks/backends/database/migrations/0009_remove_results_field.py
django_tasks/backends/database/migrations/0010_alter_dbtaskresult_status.py
django_tasks/backends/database/migrations/0011_rename_complete_status.py
django_tasks/backends/database/migrations/0012_add_separate_exception_fields.py
django_tasks/backends/database/migrations/0013_separate_exception_fields.py
django_tasks/backends/database/migrations/0014_remove_dbtaskresult_exception_data.py
django_tasks/backends/database/migrations/0015_correctly_order_run_after.py
django_tasks-0.10.0.dist-info/licenses/LICENSE
django_tasks-0.10.0.dist-info/METADATA
django_tasks-0.10.0.dist-info/WHEEL
django_tasks-0.10.0.dist-info/top_level.txt
django_tasks-0.10.0.dist-info/RECORD
