Metadata-Version: 2.4
Name: django-tasks
Version: 0.10.0
Summary: An implementation and backport of background workers and tasks in Django
Author: Jake Howard
License-Expression: BSD-3-Clause
Project-URL: Source, https://github.com/RealOrangeOne/django-tasks
Project-URL: Issues, https://github.com/RealOrangeOne/django-tasks/issues
Project-URL: Changelog, https://github.com/RealOrangeOne/django-tasks/releases
Classifier: Development Status :: 4 - Beta
Classifier: Programming Language :: Python :: 3
Classifier: Programming Language :: Python :: 3.10
Classifier: Programming Language :: Python :: 3.11
Classifier: Programming Language :: Python :: 3.12
Classifier: Programming Language :: Python :: 3.13
Classifier: Programming Language :: Python :: 3.14
Classifier: Programming Language :: Python :: Implementation :: CPython
Classifier: Environment :: Web Environment
Classifier: Framework :: Django
Classifier: Framework :: Django
Classifier: Framework :: Django :: 4.2
Classifier: Framework :: Django :: 5.0
Classifier: Framework :: Django :: 5.1
Classifier: Framework :: Django :: 5.2
Classifier: Framework :: Django :: 6.0
Classifier: Intended Audience :: Developers
Classifier: Operating System :: OS Independent
Classifier: Natural Language :: English
Classifier: Topic :: Internet :: WWW/HTTP
Classifier: Typing :: Typed
Requires-Python: >=3.10
License-File: LICENSE
Requires-Dist: Django>=4.2
Requires-Dist: typing_extensions
Requires-Dist: django-stubs-ext
Provides-Extra: dev
Requires-Dist: ruff; extra == "dev"
Requires-Dist: coverage; extra == "dev"
Requires-Dist: django-stubs[compatible-mypy]; extra == "dev"
Requires-Dist: dj-database-url; extra == "dev"
Requires-Dist: django-tasks[rq]; extra == "dev"
Requires-Dist: fakeredis; extra == "dev"
Provides-Extra: mysql
Requires-Dist: mysqlclient; extra == "mysql"
Provides-Extra: postgres
Requires-Dist: psycopg[binary]; extra == "postgres"
Provides-Extra: rq
Requires-Dist: django-rq; extra == "rq"
Requires-Dist: rq>=2.5; extra == "rq"
Requires-Dist: rq_scheduler; extra == "rq"
Dynamic: license-file
